bech32py/__init__.py
bech32py/bech32.py
savingsatoshi_bech32py-0.2.1.dist-info/METADATA
savingsatoshi_bech32py-0.2.1.dist-info/WHEEL
savingsatoshi_bech32py-0.2.1.dist-info/RECORD
